{
	"o_reglages": {
		"arr_s_batiments_disponibles": [ "Autel", "Cave", "Moulin", "Entrepot" ],
		"arr_s_tours_disponibles": [ "TourMitraillette", "TourShotGun" ],
		"arr_s_unites_disponibles": [ "Soldat", "Chevalier" ],
		"arr_s_superunites_disponibles": [ "SuperSoldat", "SuperChevalier" ],
		"arr_s_unites_speciales_disponibles": [ "Assassin", "Barbare", "Bagarreur" ],
		"arr_s_ennemis_disponibles": [ "MonstresBase", "MonstresBoxeurs" ]
	},
	"o_vagues": {
		"i_nb_rounds_avant_premiere_vague": 30,
		"o_structure_vagues": [
			{
				"i_tps": 3,
				"s_chemin_1": "Monstres Base",
				"s_chemin_2": "Monstres Base",
				"s_chemin_3": "Monstres Base"
			},
			{
				"i_tps": 4,
				"s_chemin_1": " ",
				"s_chemin_2": " ",
				"s_chemin_3": " "
			},
			{
				"i_tps": 5,
				"s_chemin_1": " ",
				"s_chemin_2": " ",
				"s_chemin_3": " "
			},



			{
				"i_tps": 9,
				"s_chemin_1": "Monstres Base",
				"s_chemin_2": "Monstres Base",
				"s_chemin_3": "Monstres Base"
			}
		]
	},
	"i_nb_rounds_carte": 5
}